setup.py
sshsec/__init__.py
sshsec/__main__.py
sshsec/_version.py
sshsec/scanner.py
sshsec/ssh.py
sshsec.egg-info/PKG-INFO
sshsec.egg-info/SOURCES.txt
sshsec.egg-info/dependency_links.txt
sshsec.egg-info/top_level.txt