Metadata-Version: 1.1
Name: sshsec
Version: 1.3.1
Summary: SSH server configuration tester
Home-page: https://github.com/Knio/sshsec
Author: Tom Flanagan
Author-email: tom@zkpq.ca
License: MIT
Keywords: ssh server configuration security networking
Platform: UNKNOWN
Classifier: Intended Audience :: Developers
Classifier: Intended Audience :: System Administrators
Classifier: License :: OSI Approved :: MIT License
Classifier: Operating System :: OS Independent
Classifier: Programming Language :: Python
Classifier: Programming Language :: Python :: 3
Classifier: Topic :: Internet
Classifier: Topic :: Security
Classifier: Topic :: Security :: Cryptography
Classifier: Topic :: Utilities
